MANIFEST.in
README.md
requirements.txt
setup.py
bin/sunday_install
pysunday.egg-info/PKG-INFO
pysunday.egg-info/SOURCES.txt
pysunday.egg-info/dependency_links.txt
pysunday.egg-info/requires.txt
pysunday.egg-info/top_level.txt
src/__init__.py
src/config.ini
src/core/MultiThread.py
src/core/__init__.py
src/core/aesCbc.py
src/core/auth.py
src/core/cachevar.py
src/core/checkPacNet.py
src/core/cmdexec.py
src/core/common.py
src/core/enver.py
src/core/fetch.py
src/core/getConfig.py
src/core/getEnv.py
src/core/getException.py
src/core/getParser.py
src/core/globalKeyMaps.py
src/core/globalvar.py
src/core/init.py
src/core/inner.py
src/core/logger.py
src/core/paths.py
src/core/premust.py
src/core/printTable.py
src/login/__init__.py
src/tools/__init__.py
src/utils/Email.py
src/utils/LoginBase.py
src/utils/__init__.py
src/utils/cryptanalyst.py
src/utils/cryptanalyst_js.py
src/utils/image.py
src/utils/initOptions.py
src/utils/md5.py
src/utils/tools.py
src/utils/cryptanalysis/aesToolsNsrd.js
src/utils/cryptanalysis/crypto.js
src/utils/cryptanalysis/cryptojs.js
src/utils/cryptanalysis/decrypt_aestoolsnsrd.js
src/utils/cryptanalysis/decrypt_cryptojs_ECB.js
src/utils/cryptanalysis/decrypt_sm4.js
src/utils/cryptanalysis/encrypt_cryptojs_ECB.js
src/utils/cryptanalysis/encrypt_jsencrypt.js
src/utils/cryptanalysis/encrypt_jsencrypt_hex.js
src/utils/cryptanalysis/encrypt_sm2.js
src/utils/cryptanalysis/encrypt_sm4.js
src/utils/cryptanalysis/jsencrypt.js
src/utils/cryptanalysis/sm2.js
src/utils/cryptanalysis/sm3.js
src/utils/cryptanalysis/sm4.js